climetlab_cems_flood/__init__.py
climetlab_cems_flood/_version.py
climetlab_cems_flood/api.py
climetlab_cems_flood/glofas_forecast.py
climetlab_cems_flood/glofas_historical.py
climetlab_cems_flood/glofas_reforecast.py
climetlab_cems_flood/glofas_seasonal.py
climetlab_cems_flood/glofas_seasonal_reforecast.py
climetlab_cems_flood/test.py
climetlab_cems_flood/utils.py
climetlab_cems_flood/.ipynb_checkpoints/__init__-checkpoint.py
climetlab_cems_flood/.ipynb_checkpoints/api-checkpoint.py
climetlab_cems_flood/.ipynb_checkpoints/glofas_historical-checkpoint.py
climetlab_cems_flood/.ipynb_checkpoints/test-checkpoint.py
climetlab_cems_flood/data/po_basin.geojson
climetlab_cems_flood/data/static/img.png
climetlab_cems_flood-0.2.6.dist-info/LICENSE
climetlab_cems_flood-0.2.6.dist-info/METADATA
climetlab_cems_flood-0.2.6.dist-info/WHEEL
climetlab_cems_flood-0.2.6.dist-info/entry_points.txt
climetlab_cems_flood-0.2.6.dist-info/top_level.txt
climetlab_cems_flood-0.2.6.dist-info/zip-safe
climetlab_cems_flood-0.2.6.dist-info/RECORD
