Metadata-Version: 2.1
Name: climetlab-cems-flood
Version: 0.2.6
Summary: Download GloFAS Copernicus Emergency Management System dataset
Home-page: https://github.com/iacopoff/climetlab-cems-flood
Author: iacopo ferrario
Author-email: iacopo.ff@gmail.com
License: Apache License Version 2.0
Keywords: hydrology,flood,emergency,global,climate
Classifier: Development Status :: 3 - Alpha
Classifier: Intended Audience :: Developers
Classifier: License :: OSI Approved :: Apache Software License
Classifier: Programming Language :: Python :: 3
Classifier: Programming Language :: Python :: 3.6
Classifier: Programming Language :: Python :: 3.7
Classifier: Programming Language :: Python :: 3.8
Classifier: Programming Language :: Python :: 3.9
Classifier: Programming Language :: Python :: 3.10
Classifier: Programming Language :: Python :: Implementation :: CPython
Classifier: Operating System :: OS Independent
License-File: LICENSE
Requires-Dist: climetlab (>=0.9.0)
